AUTHORS.txt
CHANGES.txt
LICENSE.txt
MANIFEST.in
README.txt
setup.py
tipfy/__init__.py
tipfy.ext.auth.openid.egg-info/PKG-INFO
tipfy.ext.auth.openid.egg-info/SOURCES.txt
tipfy.ext.auth.openid.egg-info/dependency_links.txt
tipfy.ext.auth.openid.egg-info/namespace_packages.txt
tipfy.ext.auth.openid.egg-info/not-zip-safe
tipfy.ext.auth.openid.egg-info/requires.txt
tipfy.ext.auth.openid.egg-info/top_level.txt
tipfy/ext/__init__.py
tipfy/ext/auth/__init__.py
tipfy/ext/auth/openid.py